[
  {
    "title": "S&P 500 Gains and Losses Today: Index Ticks Higher Ahead of This Week's Fed Decision",
    "published": 1742243527
  },
  {
    "title": "Energy Stocks Power S&P 500 Upside; Amazon, Google Make Nuclear Pledge",
    "published": 1741962278
  },
  {
    "title": "AES to Gain From Renewable Expansion & Rising Presence in LNG Space",
    "published": 1741614660
  },
  {
    "title": "3 Magnificent S&P 500 Dividend Stocks Down 20% to 63% to Buy and Hold Forever",
    "published": 1741509300
  },
  {
    "title": "BofA upgrades Vistra, AES stock ratings on growth outlook",
    "published": 1741109668
  },
  {
    "title": "AES Corp.'s Q4 Earnings Beat Estimates, Revenues Decline Y/Y",
    "published": 1741019400
  },
  {
    "title": "Company News for Mar 3, 2025",
    "published": 1740991500
  },
  {
    "title": "Should We Be Delighted With The AES Corporation's (NYSE:AES) ROE Of 9.2%?",
    "published": 1740836410
  }
]